{
	"afak": 8295,
	"aghb": 8296,
	"arab": 8297,
	"armi": 8298,
	"armn": 8299,
	"avst": 8300,
	"bali": 8301,
	"bamu": 8302,
	"bass": 8303,
	"batk": 8304,
	"beng": 8305,
	"blis": 8306,
	"bopo": 8307,
	"brah": 8308,
	"brai": 8309,
	"bugi": 8310,
	"buhd": 8311,
	"cakm": 8312,
	"cans": 8313,
	"cari": 8314,
	"cham": 8315,
	"cher": 8316,
	"cirt": 8317,
	"copt": 8318,
	"cprt": 8319,
	"cyrl": 8320,
	"cyrs": 8321,
	"deva": 8322,
	"dsrt": 8323,
	"dupl": 8324,
	"egyd": 8325,
	"egyh": 8326,
	"egyp": 8327,
	"elba": 8328,
	"ethi": 8329,
	"geok": 8330,
	"geor": 8331,
	"glag": 8332,
	"goth": 8333,
	"gran": 8334,
	"grek": 8335,
	"gujr": 8336,
	"guru": 8337,
	"hang": 8338,
	"hani": 8339,
	"hano": 8340,
	"hans": 8341,
	"hant": 8342,
	"hebr": 8343,
	"hira": 8344,
	"hluw": 8345,
	"hmng": 8346,
	"hrkt": 8347,
	"hung": 8348,
	"inds": 8349,
	"ital": 8350,
	"java": 8351,
	"jpan": 8352,
	"jurc": 8353,
	"kali": 8354,
	"kana": 8355,
	"khar": 8356,
	"khmr": 8357,
	"khoj": 8358,
	"knda": 8359,
	"kore": 8360,
	"kpel": 8361,
	"kthi": 8362,
	"lana": 8363,
	"laoo": 8364,
	"latf": 8365,
	"latg": 8366,
	"latn": 8367,
	"lepc": 8368,
	"limb": 8369,
	"lina": 8370,
	"linb": 8371,
	"lisu": 8372,
	"loma": 8373,
	"lyci": 8374,
	"lydi": 8375,
	"mahj": 8376,
	"mand": 8377,
	"mani": 8378,
	"maya": 8379,
	"mend": 8380,
	"merc": 8381,
	"mero": 8382,
	"mlym": 8383,
	"mong": 8384,
	"moon": 8385,
	"mroo": 8386,
	"mtei": 8387,
	"mymr": 8388,
	"narb": 8389,
	"nbat": 8390,
	"nkgb": 8391,
	"nkoo": 8392,
	"nshu": 8393,
	"ogam": 8394,
	"olck": 8395,
	"orkh": 8396,
	"orya": 8397,
	"osma": 8398,
	"palm": 8399,
	"perm": 8400,
	"phag": 8401,
	"phli": 8402,
	"phlp": 8403,
	"phlv": 8404,
	"phnx": 8405,
	"plrd": 8406,
	"prti": 8407,
	"qaaa..qabx": 8408,
	"rjng": 8409,
	"roro": 8410,
	"runr": 8411,
	"samr": 8412,
	"sara": 8413,
	"sarb": 8414,
	"saur": 8415,
	"sgnw": 8416,
	"shaw": 8417,
	"shrd": 8418,
	"sind": 8419,
	"sinh": 8420,
	"sora": 8421,
	"sund": 8422,
	"sylo": 8423,
	"syrc": 8424,
	"syre": 8425,
	"syrj": 8426,
	"syrn": 8427,
	"tagb": 8428,
	"takr": 8429,
	"tale": 8430,
	"talu": 8431,
	"taml": 8432,
	"tang": 8433,
	"tavt": 8434,
	"telu": 8435,
	"teng": 8436,
	"tfng": 8437,
	"tglg": 8438,
	"thaa": 8439,
	"thai": 8440,
	"tibt": 8441,
	"tirh": 8442,
	"ugar": 8443,
	"vaii": 8444,
	"visp": 8445,
	"wara": 8446,
	"wole": 8447,
	"xpeo": 8448,
	"xsux": 8449,
	"yiii": 8450,
	"zinh": 8451,
	"zmth": 8452,
	"zsym": 8453,
	"zxxx": 8454,
	"zyyy": 8455,
	"zzzz": 8456
}
