{
	"1901": 8778,
	"1994": 8780,
	"1996": 8781,
	"1606nict": 8776,
	"1694acad": 8777,
	"1959acad": 8779,
	"alalc97": 8782,
	"aluku": 8783,
	"arevela": 8784,
	"arevmda": 8785,
	"baku1926": 8786,
	"balanka": 8787,
	"barla": 8788,
	"bauddha": 8789,
	"biscayan": 8790,
	"biske": 8791,
	"bohoric": 8792,
	"boont": 8793,
	"dajnko": 8794,
	"ekavsk": 8795,
	"emodeng": 8796,
	"fonipa": 8797,
	"fonupa": 8798,
	"fonxsamp": 8799,
	"hepburn": 8800,
	"heploc": 8801,
	"hognorsk": 8802,
	"ijekavsk": 8803,
	"itihasa": 8804,
	"jauer": 8805,
	"jyutping": 8806,
	"kkcor": 8807,
	"kscor": 8808,
	"laukika": 8809,
	"lipaw": 8810,
	"luna1918": 8811,
	"metelko": 8812,
	"monoton": 8813,
	"ndyuka": 8814,
	"nedis": 8815,
	"njiva": 8816,
	"nulik": 8817,
	"osojs": 8818,
	"pamaka": 8819,
	"petr1708": 8820,
	"pinyin": 8821,
	"polyton": 8822,
	"puter": 8823,
	"rigik": 8824,
	"rozaj": 8825,
	"rumgr": 8826,
	"scotland": 8827,
	"scouse": 8828,
	"solba": 8829,
	"sotav": 8830,
	"surmiran": 8831,
	"sursilv": 8832,
	"sutsilv": 8833,
	"tarask": 8834,
	"uccor": 8835,
	"ucrcor": 8836,
	"ulster": 8837,
	"unifon": 8838,
	"vaidika": 8839,
	"valencia": 8840,
	"vallader": 8841,
	"wadegile": 8842
}
